my_package/__init__.py
my_package/cli.py
my_package_pythonboilerplate_vaibhav-0.1.1.dist-info/METADATA
my_package_pythonboilerplate_vaibhav-0.1.1.dist-info/WHEEL
my_package_pythonboilerplate_vaibhav-0.1.1.dist-info/entry_points.txt
my_package_pythonboilerplate_vaibhav-0.1.1.dist-info/top_level.txt
my_package_pythonboilerplate_vaibhav-0.1.1.dist-info/RECORD
