Metadata-Version: 2.4
Name: my_package_pythonboilerplate_vaibhav
Version: 0.1.1
Summary: Example Python boilerplate
Author-email: Vaibhav Gupta <vaibhav.gupta@infocusp.com>
Requires-Python: >=3.11
Requires-Dist: click
Provides-Extra: dev
Requires-Dist: pytest; extra == "dev"
Requires-Dist: pytest-cov; extra == "dev"
Requires-Dist: black; extra == "dev"
Requires-Dist: isort; extra == "dev"
Requires-Dist: ruff; extra == "dev"
Requires-Dist: mypy; extra == "dev"
Requires-Dist: pre-commit; extra == "dev"
